CHANGES.txt
README.txt
buildout.cfg
setup.py
bootstrap/bootstrap.py
src/zope/__init__.py
src/zope.bforest.egg-info/PKG-INFO
src/zope.bforest.egg-info/SOURCES.txt
src/zope.bforest.egg-info/dependency_links.txt
src/zope.bforest.egg-info/namespace_packages.txt
src/zope.bforest.egg-info/not-zip-safe
src/zope.bforest.egg-info/requires.txt
src/zope.bforest.egg-info/top_level.txt
src/zope/bforest/__init__.py
src/zope/bforest/bforest.py
src/zope/bforest/bforest.txt
src/zope/bforest/periodic.py
src/zope/bforest/periodic.txt
src/zope/bforest/tests.py
src/zope/bforest/utils.py