Metadata-Version: 1.0
Name: zope.bforest
Version: 1.1.1
Summary: Mappings based transparently on multiple BTrees; good for rotating caches and
